BGP_Forecast_Modules/Database.py
BGP_Forecast_Modules/ROAs_Collector.py
BGP_Forecast_Modules/Utilities.py
BGP_Forecast_Modules/__init__.py
BGP_Forecast_Modules/config.ini
BGP_Forecast_Modules/main.py
BGP_Forecast_Modules-0.0.2.dist-info/AUTHORS
BGP_Forecast_Modules-0.0.2.dist-info/LICENSE
BGP_Forecast_Modules-0.0.2.dist-info/METADATA
BGP_Forecast_Modules-0.0.2.dist-info/WHEEL
BGP_Forecast_Modules-0.0.2.dist-info/top_level.txt
BGP_Forecast_Modules-0.0.2.dist-info/RECORD
