Metadata-Version: 2.1
Name: BGP-Forecast-Modules
Version: 0.0.2
Summary: BGP Forecast Project.
Home-page: https://github.com/xinyuwang1209/BGP_Forecast_Modules.git
Author: Xinyu Wang
Author-email: xinyuwang1209@gmail.com
License: UNKNOWN
Keywords: Xinyu, xinyu, pypi, package, rpki
Platform: any
Classifier: Environment :: Console
Classifier: Intended Audience :: Developers
Classifier: License :: OSI Approved :: MIT License
Classifier: Operating System :: OS Independent
Classifier: Programming Language :: Python
Classifier: Programming Language :: Python :: 3
Requires-Dist: ipaddress
Requires-Dist: numpy
Requires-Dist: pandas
Requires-Dist: pathos
Requires-Dist: psycopg2
Requires-Dist: requests
Requires-Dist: sqlalchemy
